GPGame/__init__.py
GPGame/components.py
GPGame/engine.py
GPGame-2020.0.2.dist-info/LICENSE.txt
GPGame-2020.0.2.dist-info/METADATA
GPGame-2020.0.2.dist-info/WHEEL
GPGame-2020.0.2.dist-info/top_level.txt
GPGame-2020.0.2.dist-info/RECORD
