Metadata-Version: 2.1
Name: GPGame
Version: 2020.0.2
Summary: An abstraction layer on the Kivy GPU accelerated engine.
Home-page: https://github.com/Nv7-GitHub/GPGame
Author: Nishant Vikramaditya
Author-email: junk4Nv7@gmail.com
License: UNKNOWN
Platform: UNKNOWN
Classifier: Programming Language :: Python :: 3
Classifier: License :: OSI Approved :: MIT License
Classifier: Operating System :: OS Independent
Requires-Python: >=3.6
Requires-Dist: Kivy
